tsup/.DS_Store
tsup/VERSION
tsup/__init__.py
tsup/setting.py
tsup/botright/VERSION
tsup/botright/__init__.py
tsup/botright/botright.py
tsup/botright/modules/__init__.py
tsup/botright/modules/faker.py
tsup/botright/modules/names.txt
tsup/botright/modules/passwords.txt
tsup/botright/modules/proxy_manager.py
tsup/botright/modules/playwright_mock/__init__.py
tsup/botright/modules/playwright_mock/browser.py
tsup/botright/modules/playwright_mock/element_handle.py
tsup/botright/modules/playwright_mock/frame.py
tsup/botright/modules/playwright_mock/frame_locator.py
tsup/botright/modules/playwright_mock/js_handle.py
tsup/botright/modules/playwright_mock/locator.py
tsup/botright/modules/playwright_mock/mouse.py
tsup/botright/modules/playwright_mock/page.py
tsup/db/__init__.py
tsup/db/exceldb.py
tsup/db/exceldb_pandas.py
tsup/db/memorydb.py
tsup/db/mongodb.py
tsup/db/mysqldb.py
tsup/db/redisdb.py
tsup/db/sqlite.py
tsup/db/tdengine.py
tsup/douyin/__init__.py
tsup/douyin/douyin_upload.py
tsup/network/__init__.py
tsup/network/item.py
tsup/network/load_proxy_extension.py
tsup/network/proxy_pool.py
tsup/network/request.py
tsup/network/response.py
tsup/network/selector.py
tsup/network/user_agent.py
tsup/network/downloader/__init__.py
tsup/network/downloader/_playwright.py
tsup/network/downloader/_requests.py
tsup/network/downloader/_selenium.py
tsup/network/downloader/base.py
tsup/network/user_pool/__init__.py
tsup/network/user_pool/base_user_pool.py
tsup/network/user_pool/gold_user_pool.py
tsup/network/user_pool/guest_user_pool.py
tsup/network/user_pool/normal_user_pool.py
tsup/tiktok/TiktokUpload.py
tsup/tiktok/__init__.py
tsup/tiktok/models/__init__.py
tsup/tiktok/models/deferred_collectors.py
tsup/tiktok/models/queries.py
tsup/tiktok/models/signing.py
tsup/tiktok/models/video.py
tsup/tiktok/offical_API/__init__.py
tsup/tiktok/offical_API/python-tiktok.py
tsup/tiktok/pl/TiktokUpload.py
tsup/tiktok/pl/__init__.py
tsup/tiktok/selenium/Constant.py
tsup-0.1.16.dist-info/LICENSE
tsup-0.1.16.dist-info/METADATA
tsup-0.1.16.dist-info/WHEEL
tsup-0.1.16.dist-info/top_level.txt
tsup-0.1.16.dist-info/RECORD
