Metadata-Version: 2.1
Name: tsup
Version: 0.1.16
Summary: using playwright and selenium to upload and schedule publish video on social media platform like youtube,tiktok,douyin etc.
Home-page: https://github.com/wanghaisheng/tiktoka-studio-uploader
Download-URL: https://github.com/wanghaisheng/tiktoka-studio-uploader/tarball/version
Author: wanghaisheng
Author-email: admin@tiktokastudio.com
License: MIT
Classifier: Programming Language :: Python :: 3
Classifier: License :: OSI Approved :: MIT License
Classifier: Operating System :: OS Independent
Requires-Python: >=3.6
License-File: LICENSE
Requires-Dist: playwright
